sales_report_sk24/__init__.py
sales_report_sk24/__main__.py
sales_report_sk24/report_generator.py
sales_report_sk24-0.1.0.dist-info/METADATA
sales_report_sk24-0.1.0.dist-info/WHEEL
sales_report_sk24-0.1.0.dist-info/entry_points.txt
sales_report_sk24-0.1.0.dist-info/top_level.txt
sales_report_sk24-0.1.0.dist-info/RECORD
