Metadata-Version: 2.1
Name: sales-report-sk24
Version: 0.1.0
Summary: Пакет для составления отчёта по продажам
Author-email: Stanislav Kuleshov <phtschmth171@gmail.com>
Requires-Dist: pandas
